easychatgpt/__init__.py
easychatgpt/chatgpt.py
easychatgpt/exceptions.py
easychatgpt-0.0.8.dist-info/LICENSE
easychatgpt-0.0.8.dist-info/METADATA
easychatgpt-0.0.8.dist-info/WHEEL
easychatgpt-0.0.8.dist-info/top_level.txt
easychatgpt-0.0.8.dist-info/RECORD
