Metadata-Version: 2.1
Name: easychatgpt
Version: 0.0.8
Summary: An unofficial yet elegant interface of the ChatGPT API using browser automation that bypasses cloudflare detection and recaptchas.
Home-page: https://github.com/acheong08/ChatGPT
Author: LanLan
Author-email: 3281448091@proton.me
License: GNU General Public License v2.0
License-File: LICENSE
Requires-Dist: selenium (~=4.7.2)
Requires-Dist: undetected-chromedriver (~=3.1.7)
Requires-Dist: pypasser
Requires-Dist: pocketsphinx
